odoo/addons/base_maintenance/README.rst
odoo/addons/base_maintenance/__init__.py
odoo/addons/base_maintenance/__manifest__.py
odoo/addons/base_maintenance/i18n/base_maintenance.pot
odoo/addons/base_maintenance/i18n/es.po
odoo/addons/base_maintenance/i18n/it.po
odoo/addons/base_maintenance/models/__init__.py
odoo/addons/base_maintenance/models/maintenance_team.py
odoo/addons/base_maintenance/readme/CONTRIBUTORS.rst
odoo/addons/base_maintenance/readme/DESCRIPTION.rst
odoo/addons/base_maintenance/security/ir.model.access.csv
odoo/addons/base_maintenance/security/maintenance_security.xml
odoo/addons/base_maintenance/static/description/icon.png
odoo/addons/base_maintenance/static/description/index.html
odoo/addons/base_maintenance/views/maintenance_request_views.xml
odoo/addons/base_maintenance/views/maintenance_team_views.xml
odoo11_addon_base_maintenance-11.0.1.0.0.99.dev10.dist-info/METADATA
odoo11_addon_base_maintenance-11.0.1.0.0.99.dev10.dist-info/WHEEL
odoo11_addon_base_maintenance-11.0.1.0.0.99.dev10.dist-info/top_level.txt
odoo11_addon_base_maintenance-11.0.1.0.0.99.dev10.dist-info/RECORD
